{
  "AffectedFields": [
    "t.1"
  ],
  "CertificateType": "Test",
  "Country": "NL",
  "Description": [
    {
      "desc": "At most one test-event.",
      "lang": "en"
    },
    {
      "desc": "Höchstens ein test-Ereignis.",
      "lang": "de"
    },
    {
      "desc": "Au maximum un événement de test.",
      "lang": "fr"
    },
    {
      "desc": "Como máximo un evento de test.",
      "lang": "es"
    },
    {
      "desc": "Al massimo un test-evento.",
      "lang": "it"
    },
    {
      "desc": "Maximaal één testgebeurtenis.",
      "lang": "nl"
    }
  ],
  "Engine": "CERTLOGIC",
  "EngineVersion": "0.7.5",
  "Identifier": "TR-NL-0000",
  "Logic": {
    "!": [
      {
        "var": "payload.t.1"
      }
    ]
  },
  "SchemaVersion": "1.0.0",
  "Type": "Acceptance",
  "ValidFrom": "2022-06-02T00:00:00+01:00",
  "ValidTo": "2030-06-01T00:00:00Z",
  "Version": "1.1.3"
}
